taskipy/__init__.py
taskipy/cli.py
taskipy/exceptions.py
taskipy/list.py
taskipy/py.typed
taskipy/pyproject.py
taskipy/task.py
taskipy/task_runner.py
taskipy/variable.py
taskipy-1.12.2.dist-info/LICENSE
taskipy-1.12.2.dist-info/METADATA
taskipy-1.12.2.dist-info/WHEEL
taskipy-1.12.2.dist-info/entry_points.txt
taskipy-1.12.2.dist-info/RECORD
