Metadata-Version: 2.1
Name: taskipy
Version: 1.12.2
Summary: tasks runner for python projects
Home-page: https://github.com/taskipy/taskipy
License: MIT
Keywords: tasks,task runner,development
Author: Roy Sommer
Author-email: roy@sommer.co.il
Requires-Python: >=3.6,<4.0
Classifier: Intended Audience :: Developers
Classifier: License :: OSI Approved :: MIT License
Classifier: Programming Language :: Python :: 3
Classifier: Programming Language :: Python :: 3.6
Classifier: Programming Language :: Python :: 3.7
Classifier: Programming Language :: Python :: 3.8
Classifier: Programming Language :: Python :: 3.9
Classifier: Programming Language :: Python :: 3.10
Classifier: Programming Language :: Python :: 3.11
Classifier: Programming Language :: Python :: 3.12
Classifier: Topic :: Software Development :: Build Tools
Requires-Dist: colorama (>=0.4.4,<0.5.0)
Requires-Dist: mslex (>=1.1.0,<2.0.0) ; sys_platform == "win32"
Requires-Dist: psutil (>=5.7.2,<6.0.0)
Requires-Dist: tomli (>=1.2.3,<2.0.0) ; python_version >= "3.6" and python_version < "3.7"
Requires-Dist: tomli (>=2.0.1,<3.0.0) ; python_version >= "3.7" and python_version < "4.0"
Project-URL: Repository, https://github.com/taskipy/taskipy
